[
  {"id": "1", "songName": "Lemon", "singer": "米津玄師", "language": "Japanese", "remark": "热门歌曲", "captainRequestable": true},
  {"id": "2", "songName": "Pretender", "singer": "Official髭男dism", "language": "Japanese", "remark": "", "captainRequestable": true},
  {"id": "3", "songName": "Shape of You", "singer": "Ed Sheeran", "language": "English", "remark": "舞曲", "captainRequestable": false},
  {"id": "4", "songName": "爱你", "singer": "周杰伦", "language": "Mandarin", "pinyinInitial": "A", "remark": "经典", "captainRequestable": true},
  {"id": "5", "songName": "Bling Bling", "singer": "iKON", "language": "Other", "remark": "韩语歌", "captainRequestable": false},
  {"id": "6", "songName": "北京欢迎你", "singer": "群星", "language": "Mandarin", "pinyinInitial": "B", "remark": "奥运歌曲", "captainRequestable": true},
  {"id": "7", "songName": "夜に駆ける", "singer": "YOASOBI", "language": "Japanese", "remark": "神曲", "captainRequestable": true},
  {"id": "8", "songName": "曹操", "singer": "林俊杰", "language": "Mandarin", "pinyinInitial": "C", "remark": "历史题材", "captainRequestable": true},
  {"id": "9", "songName": "Dynamite", "singer": "BTS", "language": "English", "remark": "全球热门", "captainRequestable": true},
  {"id": "10", "songName": "稻香", "singer": "周杰伦", "language": "Mandarin", "pinyinInitial": "D", "remark": "怀旧", "captainRequestable": true}
]
